.DS_Store
lofti_gaia/__init__.py
lofti_gaia/cFunctions.cpython-39-darwin.so
lofti_gaia/lofti.py
lofti_gaia/loftitools.py
lofti_gaia/test.py
lofti_gaia-2.0.8.dist-info/LICENSE
lofti_gaia-2.0.8.dist-info/METADATA
lofti_gaia-2.0.8.dist-info/WHEEL
lofti_gaia-2.0.8.dist-info/top_level.txt
lofti_gaia-2.0.8.dist-info/RECORD
