Metadata-Version: 2.1
Name: lofti-gaia
Version: 2.0.8
Summary: Orbit fitting with Gaia astrometry
Home-page: https://github.com/logan-pearce/lofti_gaia
Download-URL: https://github.com/logan-pearce/lofti_gaia/archive/2.0.4.tar.gz
Author: Logan Pearce
Author-email: loganpearce1@arizona.edu
License: MIT
Classifier: Development Status :: 5 - Production/Stable
Classifier: Intended Audience :: Science/Research
Classifier: License :: OSI Approved :: MIT License
Classifier: Programming Language :: Python :: 3 :: Only
Classifier: Programming Language :: C
License-File: LICENSE
Requires-Dist: numpy
Requires-Dist: matplotlib
Requires-Dist: astropy >=4.0.1.post1
Requires-Dist: astroquery >=0.4
Requires-Dist: sphinx ==4.0.2
Requires-Dist: ipython >=7.19.0
Requires-Dist: nbsphinx >=0.8.6
Requires-Dist: sphinx-copybutton ==0.3.1
Requires-Dist: sphinx-rtd-theme ==0.5.0
Requires-Dist: sphinxext-opengraph ==0.4.1
Requires-Dist: jinja2 >=3.0.1
